{
  "task_id": "Phase 5 Task 6",
  "task_name": "ドキュメント完成",
  "completion_date": "2026-07-03",
  "status": "COMPLETED",
  "completion_percentage": 100,
  "overview": {
    "objective": "包括的なドキュメント作成により、Naviko LABを誰でも使える・貢献できる状態にする",
    "total_documents": 4,
    "design_philosophy": "自分で考えて成長するAI"
  },
  "documents_created": {
    "API_REFERENCE.md": {
      "description": "完全なAPI仕様書",
      "target_audience": "開発者",
      "status": "completed"
    },
    "USER_GUIDE.md": {
      "description": "ユーザー向けガイド（設計思想含む）",
      "target_audience": "初心者〜中級者",
      "status": "completed"
    },
    "DEVELOPER_GUIDE.md": {
      "description": "開発者向けガイド（3層アーキテクチャ）",
      "target_audience": "貢献者・上級開発者",
      "status": "completed"
    },
    "ARCHITECTURE.md": {
      "description": "アーキテクチャドキュメント（設計思想詳細）",
      "target_audience": "アーキテクト・上級開発者",
      "status": "completed"
    }
  },
  "key_achievements": [
    "設計思想を正しく反映したドキュメント作成",
    "「自分で考えて成長するAI」の明確化",
    "3層アーキテクチャ（実行層・能力選択層・意思決定層）の文書化",
    "環境非依存性の強調",
    "ローカルPC完全同期達成"
  ],
  "conclusion": "Phase 5 Task 6完了。Naviko LABの本来の目的「製作者がPC上で行える作業は、製作者が許可すればナビ子にもできる」を正しく文書化。PowerShell経由でローカルPCに完全同期完了。"
}
